alertpix/__init__.py
alertpix/src/account.py
alertpix/src/brcode.py
alertpix/src/charges.py
alertpix/src/statics.py
alertpix-0.3.6.dist-info/METADATA
alertpix-0.3.6.dist-info/WHEEL
alertpix-0.3.6.dist-info/top_level.txt
alertpix-0.3.6.dist-info/RECORD
