Metadata-Version: 2.1
Name: alertpix
Version: 0.3.6
Summary: Python library for communication with the alertpix api
Home-page: https://github.com/JoaquimCassano/Alertpix.py
Author: Joaquim Cassano
Author-email: joaquim@cassano.com.br
License: MIT
Keywords: api,alertpix,payments,pix
Classifier: Programming Language :: Python :: 3
Classifier: License :: OSI Approved :: MIT License
Classifier: Operating System :: OS Independent
Requires-Python: >=3.7
Requires-Dist: qrcode
Requires-Dist: requests
